pyxdelta.cpython-39-darwin.so
pyxdelta/__init__.pyi
pyxdelta-0.2.2.dist-info/RECORD
pyxdelta-0.2.2.dist-info/WHEEL
pyxdelta-0.2.2.dist-info/top_level.txt
pyxdelta-0.2.2.dist-info/METADATA
pyxdelta-0.2.2.dist-info/licenses/LICENSE
