Metadata-Version: 2.1
Name: pyxdelta
Version: 0.2.2
Summary: Python interface for xdelta.
Home-page: https://github.com/Illidanz/pyxdelta
Author: Illidan
Classifier: Programming Language :: Python :: 3
Classifier: License :: OSI Approved :: MIT License
License-File: LICENSE
